pentagon_datadog/__init__.py
pentagon_datadog/dashboard.py
pentagon_datadog/downtime.py
pentagon_datadog/monitor.py
pentagon_datadog/rodd.py
pentagon_datadog/dashboards/kubernetes/resources.yml
pentagon_datadog/dashboards/kubernetes/utilization.yml
pentagon_datadog/files/dashboard.tf.jinja
pentagon_datadog/files/datadog.tf.jinja
pentagon_datadog/files/downtime.tf.jinja
pentagon_datadog/files/monitor.tf.jinja
pentagon_datadog/files/datadog/rodd-example.yaml
pentagon_datadog/monitors/aws/burst_iops.yml
pentagon_datadog/monitors/elasticsearch/cluster_state.yml
pentagon_datadog/monitors/elasticsearch/low_disk_space.yml
pentagon_datadog/monitors/gcp/disk_throttled_read_ops.yml
pentagon_datadog/monitors/gcp/disk_throttled_write_ops.yml
pentagon_datadog/monitors/gcp-quotas/backend_services_quota.yml
pentagon_datadog/monitors/gcp-quotas/buckets_quota.yml
pentagon_datadog/monitors/gcp-quotas/external_addresses_quota.yml
pentagon_datadog/monitors/gcp-quotas/firewall_quota.yml
pentagon_datadog/monitors/gcp-quotas/forwarding_rules_quota.yml
pentagon_datadog/monitors/gcp-quotas/health_checks_quota.yml
pentagon_datadog/monitors/gcp-quotas/http_proxy_quota.yml
pentagon_datadog/monitors/gcp-quotas/https_proxy_quota.yml
pentagon_datadog/monitors/gcp-quotas/images_quota.yml
pentagon_datadog/monitors/gcp-quotas/interconnects_quota.yml
pentagon_datadog/monitors/gcp-quotas/internal_address_quota.yml
pentagon_datadog/monitors/gcp-quotas/network_quota.yml
pentagon_datadog/monitors/gcp-quotas/routers_quota.yml
pentagon_datadog/monitors/gcp-quotas/routes_quota.yml
pentagon_datadog/monitors/gcp-quotas/security_policy_rules_quota.yml
pentagon_datadog/monitors/gcp-quotas/snapshots_quota.yml
pentagon_datadog/monitors/gcp-quotas/ssl_certs_quota.yml
pentagon_datadog/monitors/gcp-quotas/static_address_region_quota.yml
pentagon_datadog/monitors/gcp-quotas/static_addresses_project_quota.yml
pentagon_datadog/monitors/gcp-quotas/subnetworks_quota.yml
pentagon_datadog-1.16.0.dist-info/LICENSE
pentagon_datadog-1.16.0.dist-info/METADATA
pentagon_datadog-1.16.0.dist-info/WHEEL
pentagon_datadog-1.16.0.dist-info/top_level.txt
pentagon_datadog-1.16.0.dist-info/RECORD
