Metadata-Version: 2.1
Name: pentagon-datadog
Version: 1.16.0
Summary: Pentagon Component to install common datadog monitors
Home-page: http://reactiveops.com/
Author: ReactiveOp Inc.
Author-email: reactive@reactiveops.com
License: Apache2.0
Platform: UNKNOWN
Requires-Dist: oyaml (>=0.8)
Requires-Dist: PyYAML (>=5.0)
Requires-Dist: pentagon (>=2.4.1)
